{"Nodes":[],"ExecutionTime":"2023-04-03T12:46:19.9128758Z","GenerationTime":"0001-01-01T00:00:00","PluginUserSpecFlowId":"d02d5184-e142-46cf-8013-8babb65eb98a","CLIUserSpecFlowId":null,"ExecutionResults":[{"ContextType":"Scenario","FeatureFolderPath":"Features","FeatureTitle":"Q-Leap Landing2","ScenarioTitle":"Q-Leap Test3","ScenarioArguments":[],"Status":"OK","StepResults":[{"Duration":"00:00:05.8916290","Status":"OK","Error":null,"Outputs":null},{"Duration":"00:00:02.7674384","Status":"OK","Error":null,"Outputs":null},{"Duration":"00:00:00.0813281","Status":"OK","Error":null,"Outputs":null},{"Duration":"00:00:02.5423294","Status":"OK","Error":null,"Outputs":null},{"Duration":"00:00:00.1733270","Status":"OK","Error":null,"Outputs":null}],"Outputs":null},{"ContextType":"Scenario","FeatureFolderPath":"Features","FeatureTitle":"Q-Leap Landing2","ScenarioTitle":"Q-Leap Test4","ScenarioArguments":[],"Status":"OK","StepResults":[{"Duration":"00:00:04.7082661","Status":"OK","Error":null,"Outputs":null},{"Duration":"00:00:00.8374560","Status":"OK","Error":null,"Outputs":null},{"Duration":"00:00:00.0562624","Status":"OK","Error":null,"Outputs":null},{"Duration":"00:00:01.1409218","Status":"OK","Error":null,"Outputs":null},{"Duration":"00:00:00.1210942","Status":"OK","Error":null,"Outputs":null}],"Outputs":null},{"ContextType":"Scenario","FeatureFolderPath":"Features","FeatureTitle":"Q-Leap Landing","ScenarioTitle":"Q-Leap Test","ScenarioArguments":[],"Status":"OK","StepResults":[{"Duration":"00:00:06.0256049","Status":"OK","Error":null,"Outputs":null},{"Duration":"00:00:02.5971228","Status":"OK","Error":null,"Outputs":null},{"Duration":"00:00:00.0904556","Status":"OK","Error":null,"Outputs":null},{"Duration":"00:00:02.6396974","Status":"OK","Error":null,"Outputs":null},{"Duration":"00:00:00.1552966","Status":"OK","Error":null,"Outputs":null}],"Outputs":null},{"ContextType":"Scenario","FeatureFolderPath":"Features","FeatureTitle":"Q-Leap Landing","ScenarioTitle":"Q-Leap Test2","ScenarioArguments":[],"Status":"OK","StepResults":[{"Duration":"00:00:04.7888389","Status":"OK","Error":null,"Outputs":null},{"Duration":"00:00:00.6827329","Status":"OK","Error":null,"Outputs":null},{"Duration":"00:00:00.0562624","Status":"OK","Error":null,"Outputs":null},{"Duration":"00:00:01.6854831","Status":"OK","Error":null,"Outputs":null},{"Duration":"00:00:00.1096440","Status":"OK","Error":null,"Outputs":null}],"Outputs":null}],"StepReports":null}